notare/__init__.py
notare/analyze.py
notare/cli.py
notare/converter.py
notare/extract.py
notare/metadata.py
notare/play.py
notare/show.py
notare/transpose.py
notare/utils.py
notare-2025.12.16a0.dist-info/licenses/LICENSE
notare-2025.12.16a0.dist-info/METADATA
notare-2025.12.16a0.dist-info/WHEEL
notare-2025.12.16a0.dist-info/entry_points.txt
notare-2025.12.16a0.dist-info/top_level.txt
notare-2025.12.16a0.dist-info/RECORD
