Metadata-Version: 2.4
Name: Notare
Version: 2025.12.16a0
Summary: A swiss knife music utility for handling music score files in the command line.
Author-email: David Issa Mattos <issamattos.david@gmail.com>
License: MIT License
Project-URL: Homepage, https://github.com/davidissamattos/notare
Requires-Python: >=3.9
License-File: LICENSE
Requires-Dist: fire>=0.6
Requires-Dist: music21>=9.0
Dynamic: license-file
